{
  "version": "4.2.9",
  "flags": {},
  "shapes": [
    {
      "label": "p",
      "points": [
        [
          1028.5714285714284,
          2239.285714285714
        ],
        [
          1121.4285714285713,
          1660.7142857142856
        ],
        [
          1471.4285714285713,
          1671.4285714285713
        ],
        [
          1474.9999999999998,
          2271.428571428571
        ]
      ],
      "group_id": null,
      "shape_type": "polygon",
      "flags": {}
    }
  ],
  "imagePath": "f3c71e7d_Middle_4.png",
  "imageData": null,
  "imageHeight": 4000,
  "imageWidth": 3000
}