{
  "version": "4.2.10",
  "flags": {},
  "shapes": [
    {
      "label": "p",
      "points": [
        [
          258.0,
          3346.2727272727275
        ],
        [
          1130.7272727272725,
          3719.0
        ],
        [
          1626.181818181818,
          2423.5454545454545
        ],
        [
          1012.5454545454545,
          2146.2727272727275
        ]
      ],
      "group_id": null,
      "shape_type": "polygon",
      "flags": {}
    }
  ],
  "imagePath": "AXKRK1MOEP61J_Middle_1.jpg",
  "imageData": null,
  "imageHeight": 4032,
  "imageWidth": 3024
}