{
  "version": "4.2.9",
  "flags": {},
  "shapes": [
    {
      "label": "p",
      "points": [
        [
          2261.0,
          1469.0
        ],
        [
          3954.75,
          1537.75
        ],
        [
          3967.25,
          2606.5
        ],
        [
          2192.25,
          2587.75
        ]
      ],
      "group_id": null,
      "shape_type": "polygon",
      "flags": {}
    }
  ],
  "imagePath": "workerID_b9181b9d_Middle_06.jpg",
  "imageData": null,
  "imageHeight": 3456,
  "imageWidth": 4608
}