{
  "version": "4.2.9",
  "flags": {},
  "shapes": [
    {
      "label": "p",
      "points": [
        [
          606.9444444444445,
          1801.388888888889
        ],
        [
          636.1111111111111,
          2072.222222222222
        ],
        [
          994.4444444444445,
          2029.1666666666667
        ],
        [
          947.2222222222223,
          1791.6666666666667
        ]
      ],
      "group_id": null,
      "shape_type": "polygon",
      "flags": {}
    }
  ],
  "imagePath": "WorkerID_middle_5.jpg",
  "imageData": null,
  "imageHeight": 4608,
  "imageWidth": 2218
}