{
  "version": "4.2.9",
  "flags": {},
  "shapes": [
    {
      "label": "p",
      "points": [
        [
          592.8571428571429,
          945.2063492063492
        ],
        [
          559.5238095238095,
          376.95238095238096
        ],
        [
          221.42857142857144,
          372.1904761904762
        ],
        [
          205.55555555555554,
          942.031746031746
        ]
      ],
      "group_id": null,
      "shape_type": "polygon",
      "flags": {}
    }
  ],
  "imagePath": "mozzamit_Index_9.png",
  "imageData": null,
  "imageHeight": 1024,
  "imageWidth": 714
}