{
  "version": "4.2.10",
  "flags": {},
  "shapes": [
    {
      "label": "p",
      "points": [
        [
          910.5454545454545,
          2955.7272727272725
        ],
        [
          1774.181818181818,
          3333.0
        ],
        [
          2428.727272727273,
          1901.1818181818182
        ],
        [
          1746.909090909091,
          1651.1818181818182
        ]
      ],
      "group_id": null,
      "shape_type": "polygon",
      "flags": {}
    }
  ],
  "imagePath": "A1VY6JOGBLDZSM_Middle_1.jpg",
  "imageData": null,
  "imageHeight": 4160,
  "imageWidth": 3120
}