{
  "version": "4.2.9",
  "flags": {},
  "shapes": [
    {
      "label": "p",
      "points": [
        [
          2006.727272727273,
          3719.0
        ],
        [
          479.4545454545455,
          3309.909090909091
        ],
        [
          1347.6363636363635,
          1150.8181818181818
        ],
        [
          2556.727272727273,
          1459.909090909091
        ]
      ],
      "group_id": null,
      "shape_type": "polygon",
      "flags": {}
    }
  ],
  "imagePath": "A15KM9JJZ46MM6_Index_5.png.jpg",
  "imageData": null,
  "imageHeight": 3968,
  "imageWidth": 2976
}