{
  "version": "4.2.9",
  "flags": {},
  "shapes": [
    {
      "label": "p",
      "points": [
        [
          378.44444444444457,
          1983.3333333333335
        ],
        [
          1009.0,
          2125.0
        ],
        [
          1156.2222222222222,
          1061.111111111111
        ],
        [
          603.4444444444446,
          1000.0
        ]
      ],
      "group_id": null,
      "shape_type": "polygon",
      "flags": {}
    }
  ],
  "imagePath": "workerID_middle_7.jpg",
  "imageData": null,
  "imageHeight": 3264,
  "imageWidth": 1504
}