{
  "version": "4.2.10",
  "flags": {},
  "shapes": [
    {
      "label": "p",
      "points": [
        [
          2152.173913043478,
          2546.173913043478
        ],
        [
          1026.086956521739,
          2367.913043478261
        ],
        [
          1600.0,
          820.0869565217391
        ],
        [
          2413.043478260869,
          863.5652173913043
        ]
      ],
      "group_id": null,
      "shape_type": "polygon",
      "flags": {}
    }
  ],
  "imagePath": "A1B20A6BP27NBV_Index_1.png",
  "imageData": null,
  "imageHeight": 4000,
  "imageWidth": 3000
}