{
  "version": "4.2.9",
  "flags": {},
  "shapes": [
    {
      "label": "p",
      "points": [
        [
          268.7142857142853,
          1419.7142857142856
        ],
        [
          775.8571428571427,
          1708.9999999999998
        ],
        [
          1225.8571428571427,
          933.9999999999999
        ],
        [
          886.5714285714284,
          694.7142857142857
        ]
      ],
      "group_id": null,
      "shape_type": "polygon",
      "flags": {}
    }
  ],
  "imagePath": "workerID_Index_10.jpg",
  "imageData": null,
  "imageHeight": 3264,
  "imageWidth": 1504
}