{
  "version": "4.2.9",
  "flags": {},
  "shapes": [
    {
      "label": "b",
      "points": [
        [
          233.92957746478874,
          609.8591549295775
        ],
        [
          488.85915492957747,
          633.8028169014085
        ],
        [
          522.661971830986,
          333.80281690140845
        ],
        [
          280.4084507042254,
          323.943661971831
        ]
      ],
      "group_id": null,
      "shape_type": "polygon",
      "flags": {}
    }
  ],
  "imagePath": "microjob1.jpg",
  "imageData": null,
  "imageHeight": 1280,
  "imageWidth": 720
}