{
  "version": "4.2.9",
  "flags": {},
  "shapes": [
    {
      "label": "b",
      "points": [
        [
          128.58823529411768,
          693.2941176470589
        ],
        [
          574.4705882352941,
          762.7058823529412
        ],
        [
          634.4705882352941,
          136.8235294117647
        ],
        [
          279.17647058823536,
          86.23529411764706
        ]
      ],
      "group_id": null,
      "shape_type": "polygon",
      "flags": {}
    }
  ],
  "imagePath": "477b1815_Middle_08.jpeg",
  "imageData": null,
  "imageHeight": 1080,
  "imageWidth": 810
}